common/__init__.py
common/apps.py
common/migrations/__init__.py
common/models/__init__.py
common/models/route.py
common/models/user.py
ppf_models-0.0.1.dist-info/METADATA
ppf_models-0.0.1.dist-info/WHEEL
ppf_models-0.0.1.dist-info/top_level.txt
ppf_models-0.0.1.dist-info/RECORD
