Metadata-Version: 2.1
Name: ppf-models
Version: 0.0.1
Requires-Python: >=3.11
Requires-Dist: Django >=5.0
